{
  "cb_0_r": false,
  "cb_0_a": false,
  "cb_0_g": false,
  "cb_1_r": false,
  "cb_1_a": false,
  "cb_1_g": false,
  "cb_2_r": false,
  "cb_2_a": false,
  "cb_2_g": false,
  "cb_3_r": false,
  "cb_3_a": false,
  "cb_3_g": false,
  "cb_4_r": false,
  "cb_4_a": false,
  "cb_4_g": false,
  "cb_5_r": false,
  "cb_5_a": false,
  "cb_5_g": false,
  "cb_6_r": false,
  "cb_6_a": false,
  "cb_6_g": false,
  "cb_7_r": false,
  "cb_7_a": false,
  "cb_7_g": false,
  "cb_8_r": false,
  "cb_8_a": false,
  "cb_8_g": false,
  "cb_9_r": false,
  "cb_9_a": false,
  "cb_9_g": false,
  "cb_10_r": false,
  "cb_10_a": false,
  "cb_10_g": false,
  "cb_11_r": false,
  "cb_11_a": false,
  "cb_11_g": false,
  "cb_12_r": false,
  "cb_12_a": false,
  "cb_12_g": false,
  "cb_13_r": false,
  "cb_13_a": false,
  "cb_13_g": false,
  "cb_14_r": false,
  "cb_14_a": false,
  "cb_14_g": false,
  "cb_15_r": false,
  "cb_15_a": false,
  "cb_15_g": false,
  "cb_16_r": false,
  "cb_16_a": false,
  "cb_16_g": false,
  "cb_17_r": false,
  "cb_17_a": false,
  "cb_17_g": false,
  "cb_18_r": false,
  "cb_18_a": false,
  "cb_18_g": false,
  "cb_19_r": false,
  "cb_19_a": false,
  "cb_19_g": false,
  "cb_20_r": false,
  "cb_20_a": false,
  "cb_20_g": false,
  "cb_21_r": false,
  "cb_21_a": false,
  "cb_21_g": false,
  "cb_22_r": false,
  "cb_22_a": false,
  "cb_22_g": false,
  "cb_23_r": false,
  "cb_23_a": false,
  "cb_23_g": false,
  "cb_24_r": false,
  "cb_24_a": false,
  "cb_24_g": false,
  "cb_25_r": false,
  "cb_25_a": false,
  "cb_25_g": false,
  "cb_26_r": false,
  "cb_26_a": false,
  "cb_26_g": false,
  "cb_27_r": false,
  "cb_27_a": false,
  "cb_27_g": false,
  "cb_28_r": false,
  "cb_28_a": false,
  "cb_28_g": false,
  "cb_29_r": false,
  "cb_29_a": false,
  "cb_29_g": false,
  "cb_30_r": false,
  "cb_30_a": false,
  "cb_30_g": false,
  "cb_31_r": false,
  "cb_31_a": false,
  "cb_31_g": false,
  "cb_32_r": false,
  "cb_32_a": false,
  "cb_32_g": false,
  "cb_33_r": false,
  "cb_33_a": false,
  "cb_33_g": false,
  "cb_34_r": false,
  "cb_34_a": false,
  "cb_34_g": false,
  "cb_35_r": false,
  "cb_35_a": false,
  "cb_35_g": false,
  "cb_36_r": false,
  "cb_36_a": false,
  "cb_36_g": false,
  "cb_37_r": false,
  "cb_37_a": false,
  "cb_37_g": false,
  "cb_38_r": false,
  "cb_38_a": false,
  "cb_38_g": false,
  "cb_39_r": false,
  "cb_39_a": false,
  "cb_39_g": false,
  "cb_40_r": false,
  "cb_40_a": false,
  "cb_40_g": false,
  "cb_41_r": false,
  "cb_41_a": false,
  "cb_41_g": false,
  "cb_42_r": false,
  "cb_42_a": false,
  "cb_42_g": false,
  "cb_43_r": false,
  "cb_43_a": false,
  "cb_43_g": false,
  "cb_44_r": false,
  "cb_44_a": false,
  "cb_44_g": false,
  "cb_45_r": false,
  "cb_45_a": false,
  "cb_45_g": false,
  "cb_46_r": false,
  "cb_46_a": false,
  "cb_46_g": false,
  "cb_47_r": false,
  "cb_47_a": false,
  "cb_47_g": false,
  "cb_48_r": false,
  "cb_48_a": false,
  "cb_48_g": false,
  "cb_49_r": false,
  "cb_49_a": false,
  "cb_49_g": false,
  "cb_50_r": false,
  "cb_50_a": false,
  "cb_50_g": false,
  "cb_51_r": false,
  "cb_51_a": false,
  "cb_51_g": false,
  "cb_52_r": false,
  "cb_52_a": false,
  "cb_52_g": false,
  "cb_53_r": false,
  "cb_53_a": false,
  "cb_53_g": false,
  "cb_54_r": false,
  "cb_54_a": false,
  "cb_54_g": false,
  "cb_55_r": false,
  "cb_55_a": false,
  "cb_55_g": false,
  "cb_56_r": false,
  "cb_56_a": false,
  "cb_56_g": false,
  "cb_57_r": false,
  "cb_57_a": false,
  "cb_57_g": false,
  "cb_58_r": false,
  "cb_58_a": false,
  "cb_58_g": false,
  "cb_59_r": false,
  "cb_59_a": false,
  "cb_59_g": false,
  "cb_60_r": false,
  "cb_60_a": false,
  "cb_60_g": false,
  "cb_61_r": false,
  "cb_61_a": false,
  "cb_61_g": false,
  "cb_62_r": false,
  "cb_62_a": false,
  "cb_62_g": false,
  "cb_63_r": false,
  "cb_63_a": false,
  "cb_63_g": false,
  "cb_64_r": false,
  "cb_64_a": false,
  "cb_64_g": false,
  "cb_65_r": false,
  "cb_65_a": false,
  "cb_65_g": false,
  "cb_66_r": false,
  "cb_66_a": false,
  "cb_66_g": false,
  "cb_67_r": false,
  "cb_67_a": false,
  "cb_67_g": false,
  "cb_68_r": false,
  "cb_68_a": false,
  "cb_68_g": false,
  "cb_69_r": false,
  "cb_69_a": false,
  "cb_69_g": false,
  "cb_70_r": false,
  "cb_70_a": false,
  "cb_70_g": false,
  "cb_71_r": false,
  "cb_71_a": false,
  "cb_71_g": false,
  "cb_72_r": false,
  "cb_72_a": false,
  "cb_72_g": false,
  "cb_73_r": false,
  "cb_73_a": false,
  "cb_73_g": false,
  "cb_74_r": false,
  "cb_74_a": false,
  "cb_74_g": false,
  "cb_75_r": false,
  "cb_75_a": false,
  "cb_75_g": false,
  "cb_76_r": false,
  "cb_76_a": false,
  "cb_76_g": false,
  "cb_77_r": false,
  "cb_77_a": false,
  "cb_77_g": false,
  "cb_78_r": false,
  "cb_78_a": false,
  "cb_78_g": false,
  "cb_79_r": false,
  "cb_79_a": false,
  "cb_79_g": false,
  "cb_80_r": false,
  "cb_80_a": false,
  "cb_80_g": false,
  "cb_81_r": false,
  "cb_81_a": false,
  "cb_81_g": false,
  "cb_82_r": false,
  "cb_82_a": false,
  "cb_82_g": false,
  "cb_83_r": false,
  "cb_83_a": false,
  "cb_83_g": false,
  "cb_84_r": false,
  "cb_84_a": false,
  "cb_84_g": false,
  "cb_85_r": false,
  "cb_85_a": false,
  "cb_85_g": false,
  "cb_86_r": false,
  "cb_86_a": false,
  "cb_86_g": false,
  "cb_87_r": false,
  "cb_87_a": false,
  "cb_87_g": false,
  "cb_88_r": false,
  "cb_88_a": false,
  "cb_88_g": false,
  "cb_89_r": false,
  "cb_89_a": false,
  "cb_89_g": false,
  "cb_90_r": false,
  "cb_90_a": false,
  "cb_90_g": false,
  "cb_91_r": false,
  "cb_91_a": false,
  "cb_91_g": false,
  "cb_92_r": false,
  "cb_92_a": false,
  "cb_92_g": false,
  "cb_93_r": false,
  "cb_93_a": false,
  "cb_93_g": false,
  "cb_94_r": false,
  "cb_94_a": false,
  "cb_94_g": false,
  "cb_95_r": false,
  "cb_95_a": false,
  "cb_95_g": false,
  "cb_96_r": false,
  "cb_96_a": false,
  "cb_96_g": false,
  "cb_97_r": false,
  "cb_97_a": false,
  "cb_97_g": false,
  "cb_98_r": false,
  "cb_98_a": false,
  "cb_98_g": false,
  "cb_99_r": false,
  "cb_99_a": false,
  "cb_99_g": false,
  "cb_100_r": false,
  "cb_100_a": false,
  "cb_100_g": false,
  "cb_101_r": false,
  "cb_101_a": false,
  "cb_101_g": false,
  "cb_102_r": false,
  "cb_102_a": false,
  "cb_102_g": false,
  "cb_103_r": false,
  "cb_103_a": false,
  "cb_103_g": false,
  "cb_104_r": false,
  "cb_104_a": false,
  "cb_104_g": false,
  "cb_105_r": false,
  "cb_105_a": false,
  "cb_105_g": false,
  "cb_106_r": false,
  "cb_106_a": false,
  "cb_106_g": false,
  "cb_107_r": false,
  "cb_107_a": false,
  "cb_107_g": false,
  "cb_108_r": false,
  "cb_108_a": false,
  "cb_108_g": false,
  "cb_109_r": false,
  "cb_109_a": false,
  "cb_109_g": false,
  "cb_110_r": false,
  "cb_110_a": false,
  "cb_110_g": false,
  "cb_111_r": false,
  "cb_111_a": false,
  "cb_111_g": false,
  "cb_112_r": false,
  "cb_112_a": false,
  "cb_112_g": false,
  "cb_113_r": false,
  "cb_113_a": false,
  "cb_113_g": false,
  "cb_114_r": false,
  "cb_114_a": false,
  "cb_114_g": false,
  "cb_115_r": false,
  "cb_115_a": false,
  "cb_115_g": false,
  "cb_116_r": false,
  "cb_116_a": false,
  "cb_116_g": false,
  "cb_117_r": false,
  "cb_117_a": false,
  "cb_117_g": false,
  "cb_118_r": false,
  "cb_118_a": false,
  "cb_118_g": false,
  "cb_119_r": false,
  "cb_119_a": false,
  "cb_119_g": false,
  "cb_120_r": false,
  "cb_120_a": false,
  "cb_120_g": false,
  "cb_121_r": false,
  "cb_121_a": false,
  "cb_121_g": false,
  "cb_122_r": false,
  "cb_122_a": false,
  "cb_122_g": false,
  "cb_123_r": false,
  "cb_123_a": false,
  "cb_123_g": false,
  "cb_124_r": false,
  "cb_124_a": false,
  "cb_124_g": false,
  "cb_125_r": false,
  "cb_125_a": false,
  "cb_125_g": false,
  "cb_126_r": false,
  "cb_126_a": false,
  "cb_126_g": false,
  "cb_127_r": false,
  "cb_127_a": false,
  "cb_127_g": false,
  "cb_128_r": false,
  "cb_128_a": false,
  "cb_128_g": false,
  "cb_129_r": false,
  "cb_129_a": false,
  "cb_129_g": false,
  "cb_130_r": false,
  "cb_130_a": false,
  "cb_130_g": false,
  "cb_131_r": false,
  "cb_131_a": false,
  "cb_131_g": false,
  "cb_132_r": false,
  "cb_132_a": false,
  "cb_132_g": false,
  "cb_133_r": false,
  "cb_133_a": false,
  "cb_133_g": false,
  "cb_134_r": false,
  "cb_134_a": false,
  "cb_134_g": false,
  "cb_135_r": false,
  "cb_135_a": false,
  "cb_135_g": false,
  "cb_136_r": false,
  "cb_136_a": false,
  "cb_136_g": false,
  "cb_137_r": false,
  "cb_137_a": false,
  "cb_137_g": false,
  "cb_138_r": false,
  "cb_138_a": false,
  "cb_138_g": false,
  "cb_139_r": false,
  "cb_139_a": false,
  "cb_139_g": false,
  "cb_140_r": false,
  "cb_140_a": false,
  "cb_140_g": false,
  "cb_141_r": false,
  "cb_141_a": false,
  "cb_141_g": false,
  "cb_142_r": false,
  "cb_142_a": false,
  "cb_142_g": false,
  "cb_143_r": false,
  "cb_143_a": false,
  "cb_143_g": false,
  "cb_144_r": false,
  "cb_144_a": false,
  "cb_144_g": false,
  "cb_145_r": false,
  "cb_145_a": false,
  "cb_145_g": false,
  "cb_146_r": false,
  "cb_146_a": false,
  "cb_146_g": false,
  "cb_147_r": false,
  "cb_147_a": false,
  "cb_147_g": false,
  "cb_148_r": false,
  "cb_148_a": false,
  "cb_148_g": false,
  "cb_149_r": false,
  "cb_149_a": false,
  "cb_149_g": false,
  "cb_150_r": false,
  "cb_150_a": false,
  "cb_150_g": false,
  "cb_151_r": false,
  "cb_151_a": false,
  "cb_151_g": false,
  "cb_152_r": false,
  "cb_152_a": false,
  "cb_152_g": false,
  "cb_153_r": false,
  "cb_153_a": false,
  "cb_153_g": false,
  "cb_154_r": false,
  "cb_154_a": false,
  "cb_154_g": false,
  "cb_155_r": false,
  "cb_155_a": false,
  "cb_155_g": false,
  "cb_156_r": false,
  "cb_156_a": false,
  "cb_156_g": false,
  "cb_157_r": false,
  "cb_157_a": false,
  "cb_157_g": false,
  "cb_158_r": false,
  "cb_158_a": false,
  "cb_158_g": false,
  "cb_159_r": false,
  "cb_159_a": false,
  "cb_159_g": false,
  "cb_160_r": false,
  "cb_160_a": false,
  "cb_160_g": false,
  "cb_161_r": false,
  "cb_161_a": false,
  "cb_161_g": false,
  "cb_162_r": false,
  "cb_162_a": false,
  "cb_162_g": false,
  "cb_163_r": false,
  "cb_163_a": false,
  "cb_163_g": false,
  "cb_164_r": false,
  "cb_164_a": false,
  "cb_164_g": false,
  "cb_165_r": false,
  "cb_165_a": false,
  "cb_165_g": false,
  "cb_166_r": false,
  "cb_166_a": false,
  "cb_166_g": false,
  "cb_167_r": false,
  "cb_167_a": false,
  "cb_167_g": false,
  "cb_168_r": false,
  "cb_168_a": false,
  "cb_168_g": false,
  "cb_169_r": false,
  "cb_169_a": false,
  "cb_169_g": false,
  "cb_170_r": false,
  "cb_170_a": false,
  "cb_170_g": false,
  "cb_171_r": false,
  "cb_171_a": false,
  "cb_171_g": false,
  "cb_172_r": false,
  "cb_172_a": false,
  "cb_172_g": false,
  "cb_173_r": false,
  "cb_173_a": false,
  "cb_173_g": false,
  "cb_174_r": false,
  "cb_174_a": false,
  "cb_174_g": false,
  "cb_175_r": false,
  "cb_175_a": false,
  "cb_175_g": false,
  "cb_176_r": false,
  "cb_176_a": false,
  "cb_176_g": false,
  "cb_177_r": false,
  "cb_177_a": false,
  "cb_177_g": false,
  "cb_178_r": false,
  "cb_178_a": false,
  "cb_178_g": false,
  "cb_179_r": false,
  "cb_179_a": false,
  "cb_179_g": false,
  "cb_180_r": false,
  "cb_180_a": false,
  "cb_180_g": false,
  "cb_181_r": false,
  "cb_181_a": false,
  "cb_181_g": false,
  "cb_182_r": false,
  "cb_182_a": false,
  "cb_182_g": false,
  "cb_183_r": false,
  "cb_183_a": false,
  "cb_183_g": false,
  "cb_184_r": false,
  "cb_184_a": false,
  "cb_184_g": false,
  "cb_185_r": false,
  "cb_185_a": false,
  "cb_185_g": false,
  "cb_186_r": false,
  "cb_186_a": false,
  "cb_186_g": false,
  "cb_187_r": false,
  "cb_187_a": false,
  "cb_187_g": false,
  "cb_188_r": false,
  "cb_188_a": false,
  "cb_188_g": false,
  "cb_189_r": false,
  "cb_189_a": false,
  "cb_189_g": false,
  "cb_190_r": false,
  "cb_190_a": false,
  "cb_190_g": false,
  "cb_191_r": false,
  "cb_191_a": false,
  "cb_191_g": false,
  "cb_192_r": false,
  "cb_192_a": false,
  "cb_192_g": false,
  "cb_193_r": false,
  "cb_193_a": false,
  "cb_193_g": false,
  "cb_194_r": false,
  "cb_194_a": false,
  "cb_194_g": false,
  "cb_195_r": false,
  "cb_195_a": false,
  "cb_195_g": false,
  "cb_196_r": false,
  "cb_196_a": false,
  "cb_196_g": false,
  "cb_197_r": false,
  "cb_197_a": false,
  "cb_197_g": false,
  "cb_198_r": false,
  "cb_198_a": false,
  "cb_198_g": false,
  "cb_199_r": false,
  "cb_199_a": false,
  "cb_199_g": false,
  "cb_200_r": false,
  "cb_200_a": false,
  "cb_200_g": false,
  "cb_201_r": false,
  "cb_201_a": false,
  "cb_201_g": false,
  "cb_202_r": false,
  "cb_202_a": false,
  "cb_202_g": false,
  "cb_203_r": false,
  "cb_203_a": false,
  "cb_203_g": false,
  "cb_204_r": false,
  "cb_204_a": false,
  "cb_204_g": false,
  "cb_205_r": false,
  "cb_205_a": false,
  "cb_205_g": false,
  "cb_206_r": false,
  "cb_206_a": false,
  "cb_206_g": false,
  "cb_207_r": false,
  "cb_207_a": false,
  "cb_207_g": false,
  "cb_208_r": false,
  "cb_208_a": false,
  "cb_208_g": false,
  "cb_209_r": false,
  "cb_209_a": false,
  "cb_209_g": false,
  "cb_210_r": false,
  "cb_210_a": false,
  "cb_210_g": false,
  "cb_211_r": false,
  "cb_211_a": false,
  "cb_211_g": false,
  "cb_212_r": false,
  "cb_212_a": false,
  "cb_212_g": false,
  "cb_213_r": false,
  "cb_213_a": false,
  "cb_213_g": false,
  "cb_214_r": false,
  "cb_214_a": false,
  "cb_214_g": false,
  "cb_215_r": false,
  "cb_215_a": false,
  "cb_215_g": false,
  "cb_216_r": false,
  "cb_216_a": false,
  "cb_216_g": false,
  "cb_217_r": false,
  "cb_217_a": false,
  "cb_217_g": false,
  "cb_218_r": false,
  "cb_218_a": false,
  "cb_218_g": false,
  "cb_219_r": false,
  "cb_219_a": false,
  "cb_219_g": false,
  "cb_220_r": false,
  "cb_220_a": false,
  "cb_220_g": false,
  "cb_221_r": false,
  "cb_221_a": false,
  "cb_221_g": false,
  "cb_222_r": false,
  "cb_222_a": false,
  "cb_222_g": false,
  "cb_223_r": false,
  "cb_223_a": false,
  "cb_223_g": false,
  "cb_224_r": false,
  "cb_224_a": false,
  "cb_224_g": false,
  "cb_225_r": false,
  "cb_225_a": false,
  "cb_225_g": false,
  "cb_226_r": false,
  "cb_226_a": false,
  "cb_226_g": false,
  "cb_227_r": false,
  "cb_227_a": false,
  "cb_227_g": false,
  "cb_228_r": false,
  "cb_228_a": false,
  "cb_228_g": false,
  "cb_229_r": false,
  "cb_229_a": false,
  "cb_229_g": false,
  "cb_230_r": false,
  "cb_230_a": false,
  "cb_230_g": false,
  "cb_231_r": false,
  "cb_231_a": false,
  "cb_231_g": false,
  "cb_232_r": false,
  "cb_232_a": false,
  "cb_232_g": false,
  "cb_233_r": false,
  "cb_233_a": false,
  "cb_233_g": false,
  "cb_234_r": false,
  "cb_234_a": false,
  "cb_234_g": false,
  "cb_235_r": false,
  "cb_235_a": false,
  "cb_235_g": false,
  "cb_236_r": false,
  "cb_236_a": false,
  "cb_236_g": false,
  "cb_237_r": false,
  "cb_237_a": false,
  "cb_237_g": false,
  "cb_238_r": false,
  "cb_238_a": false,
  "cb_238_g": false,
  "cb_239_r": false,
  "cb_239_a": false,
  "cb_239_g": false,
  "cb_240_r": false,
  "cb_240_a": false,
  "cb_240_g": false,
  "cb_241_r": false,
  "cb_241_a": false,
  "cb_241_g": false,
  "cb_242_r": false,
  "cb_242_a": false,
  "cb_242_g": false,
  "cb_243_r": false,
  "cb_243_a": false,
  "cb_243_g": false,
  "cb_244_r": false,
  "cb_244_a": false,
  "cb_244_g": false,
  "cb_245_r": false,
  "cb_245_a": false,
  "cb_245_g": false,
  "cb_246_r": false,
  "cb_246_a": false,
  "cb_246_g": false,
  "cb_247_r": false,
  "cb_247_a": false,
  "cb_247_g": false,
  "cb_248_r": false,
  "cb_248_a": false,
  "cb_248_g": false,
  "cb_249_r": false,
  "cb_249_a": false,
  "cb_249_g": false,
  "cb_250_r": false,
  "cb_250_a": false,
  "cb_250_g": false,
  "cb_251_r": false,
  "cb_251_a": false,
  "cb_251_g": false,
  "cb_252_r": false,
  "cb_252_a": false,
  "cb_252_g": false,
  "cb_253_r": false,
  "cb_253_a": false,
  "cb_253_g": false,
  "cb_254_r": false,
  "cb_254_a": false,
  "cb_254_g": false,
  "cb_255_r": false,
  "cb_255_a": false,
  "cb_255_g": false,
  "cb_256_r": false,
  "cb_256_a": false,
  "cb_256_g": false,
  "cb_257_r": false,
  "cb_257_a": false,
  "cb_257_g": false,
  "cb_258_r": false,
  "cb_258_a": false,
  "cb_258_g": false,
  "cb_259_r": false,
  "cb_259_a": false,
  "cb_259_g": false,
  "cb_260_r": false,
  "cb_260_a": false,
  "cb_260_g": false,
  "cb_261_r": false,
  "cb_261_a": false,
  "cb_261_g": false,
  "cb_262_r": false,
  "cb_262_a": false,
  "cb_262_g": false,
  "cb_263_r": false,
  "cb_263_a": false,
  "cb_263_g": false,
  "cb_264_r": false,
  "cb_264_a": false,
  "cb_264_g": false,
  "cb_265_r": false,
  "cb_265_a": false,
  "cb_265_g": false,
  "cb_266_r": false,
  "cb_266_a": false,
  "cb_266_g": false,
  "cb_267_r": false,
  "cb_267_a": false,
  "cb_267_g": false,
  "cb_268_r": false,
  "cb_268_a": false,
  "cb_268_g": false,
  "cb_269_r": false,
  "cb_269_a": false,
  "cb_269_g": false,
  "cb_270_r": false,
  "cb_270_a": false,
  "cb_270_g": false,
  "cb_271_r": false,
  "cb_271_a": false,
  "cb_271_g": false,
  "cb_272_r": false,
  "cb_272_a": false,
  "cb_272_g": false,
  "cb_273_r": false,
  "cb_273_a": false,
  "cb_273_g": false,
  "cb_274_r": false,
  "cb_274_a": false,
  "cb_274_g": false,
  "cb_275_r": false,
  "cb_275_a": false,
  "cb_275_g": false,
  "cb_276_r": false,
  "cb_276_a": false,
  "cb_276_g": false,
  "cb_277_r": false,
  "cb_277_a": false,
  "cb_277_g": false,
  "cb_278_r": false,
  "cb_278_a": false,
  "cb_278_g": false,
  "cb_279_r": false,
  "cb_279_a": false,
  "cb_279_g": false,
  "cb_280_r": false,
  "cb_280_a": false,
  "cb_280_g": false,
  "cb_281_r": false,
  "cb_281_a": false,
  "cb_281_g": false,
  "cb_282_r": false,
  "cb_282_a": false,
  "cb_282_g": false,
  "cb_283_r": false,
  "cb_283_a": false,
  "cb_283_g": false,
  "cb_284_r": false,
  "cb_284_a": false,
  "cb_284_g": false,
  "cb_285_r": false,
  "cb_285_a": false,
  "cb_285_g": false,
  "cb_286_r": false,
  "cb_286_a": false,
  "cb_286_g": false,
  "cb_287_r": false,
  "cb_287_a": false,
  "cb_287_g": false,
  "cb_288_r": false,
  "cb_288_a": false,
  "cb_288_g": false,
  "cb_289_r": false,
  "cb_289_a": false,
  "cb_289_g": false,
  "cb_290_r": false,
  "cb_290_a": false,
  "cb_290_g": false,
  "cb_291_r": false,
  "cb_291_a": false,
  "cb_291_g": false,
  "cb_292_r": false,
  "cb_292_a": false,
  "cb_292_g": false,
  "cb_293_r": false,
  "cb_293_a": false,
  "cb_293_g": false,
  "cb_294_r": false,
  "cb_294_a": false,
  "cb_294_g": false,
  "cb_295_r": false,
  "cb_295_a": false,
  "cb_295_g": false,
  "cb_296_r": false,
  "cb_296_a": false,
  "cb_296_g": false,
  "cb_297_r": false,
  "cb_297_a": false,
  "cb_297_g": false,
  "cb_298_r": false,
  "cb_298_a": false,
  "cb_298_g": true,
  "cb_299_r": false,
  "cb_299_a": false,
  "cb_299_g": true,
  "cb_300_r": false,
  "cb_300_a": true,
  "cb_300_g": false,
  "cb_301_r": false,
  "cb_301_a": false,
  "cb_301_g": true,
  "cb_302_r": false,
  "cb_302_a": true,
  "cb_302_g": false,
  "cb_303_r": false,
  "cb_303_a": true,
  "cb_303_g": false,
  "cb_304_r": false,
  "cb_304_a": false,
  "cb_304_g": true,
  "cb_305_r": false,
  "cb_305_a": false,
  "cb_305_g": true,
  "cb_306_r": false,
  "cb_306_a": false,
  "cb_306_g": true,
  "cb_307_r": true,
  "cb_307_a": false,
  "cb_307_g": false,
  "cb_308_r": false,
  "cb_308_a": true,
  "cb_308_g": false,
  "cb_309_r": false,
  "cb_309_a": false,
  "cb_309_g": true,
  "cb_310_r": false,
  "cb_310_a": false,
  "cb_310_g": true,
  "cb_311_r": false,
  "cb_311_a": false,
  "cb_311_g": true,
  "cb_312_r": false,
  "cb_312_a": false,
  "cb_312_g": true,
  "cb_313_r": false,
  "cb_313_a": false,
  "cb_313_g": true,
  "cb_314_r": true,
  "cb_314_a": false,
  "cb_314_g": false,
  "cb_315_r": false,
  "cb_315_a": false,
  "cb_315_g": true,
  "cb_316_r": false,
  "cb_316_a": false,
  "cb_316_g": true,
  "cb_317_r": false,
  "cb_317_a": false,
  "cb_317_g": true,
  "cb_318_r": false,
  "cb_318_a": false,
  "cb_318_g": true,
  "cb_319_r": false,
  "cb_319_a": false,
  "cb_319_g": true,
  "cb_320_r": false,
  "cb_320_a": false,
  "cb_320_g": true,
  "cb_321_r": false,
  "cb_321_a": true,
  "cb_321_g": false,
  "cb_322_r": true,
  "cb_322_a": false,
  "cb_322_g": false,
  "cb_323_r": true,
  "cb_323_a": false,
  "cb_323_g": false,
  "cb_324_r": false,
  "cb_324_a": false,
  "cb_324_g": true,
  "cb_325_r": false,
  "cb_325_a": false,
  "cb_325_g": false,
  "cb_326_r": false,
  "cb_326_a": false,
  "cb_326_g": false,
  "cb_327_r": false,
  "cb_327_a": false,
  "cb_327_g": false,
  "cb_328_r": false,
  "cb_328_a": false,
  "cb_328_g": false,
  "cb_329_r": false,
  "cb_329_a": false,
  "cb_329_g": false,
  "cb_330_r": false,
  "cb_330_a": false,
  "cb_330_g": false,
  "cb_331_r": false,
  "cb_331_a": false,
  "cb_331_g": false,
  "cb_332_r": false,
  "cb_332_a": false,
  "cb_332_g": false,
  "cb_333_r": false,
  "cb_333_a": false,
  "cb_333_g": false,
  "cb_334_r": false,
  "cb_334_a": false,
  "cb_334_g": false,
  "cb_335_r": false,
  "cb_335_a": false,
  "cb_335_g": false,
  "cb_336_r": false,
  "cb_336_a": false,
  "cb_336_g": false,
  "cb_337_r": false,
  "cb_337_a": false,
  "cb_337_g": false,
  "cb_338_r": false,
  "cb_338_a": false,
  "cb_338_g": false,
  "cb_339_r": false,
  "cb_339_a": false,
  "cb_339_g": false,
  "cb_340_r": false,
  "cb_340_a": false,
  "cb_340_g": false,
  "cb_341_r": false,
  "cb_341_a": false,
  "cb_341_g": false,
  "cb_342_r": false,
  "cb_342_a": false,
  "cb_342_g": false,
  "cb_343_r": false,
  "cb_343_a": false,
  "cb_343_g": false,
  "cb_344_r": false,
  "cb_344_a": false,
  "cb_344_g": false,
  "cb_345_r": false,
  "cb_345_a": false,
  "cb_345_g": false,
  "cb_346_r": false,
  "cb_346_a": false,
  "cb_346_g": false,
  "cb_347_r": false,
  "cb_347_a": false,
  "cb_347_g": false,
  "cb_348_r": false,
  "cb_348_a": false,
  "cb_348_g": false,
  "cb_349_r": false,
  "cb_349_a": false,
  "cb_349_g": false,
  "cb_350_r": false,
  "cb_350_a": false,
  "cb_350_g": false,
  "cb_351_r": false,
  "cb_351_a": false,
  "cb_351_g": false,
  "cb_352_r": false,
  "cb_352_a": false,
  "cb_352_g": false,
  "cb_353_r": false,
  "cb_353_a": false,
  "cb_353_g": false,
  "cb_354_r": false,
  "cb_354_a": false,
  "cb_354_g": false,
  "cb_355_r": false,
  "cb_355_a": false,
  "cb_355_g": false,
  "cb_356_r": false,
  "cb_356_a": false,
  "cb_356_g": false,
  "cb_357_r": false,
  "cb_357_a": false,
  "cb_357_g": false,
  "cb_358_r": false,
  "cb_358_a": false,
  "cb_358_g": false,
  "cb_359_r": false,
  "cb_359_a": false,
  "cb_359_g": false,
  "cb_360_r": false,
  "cb_360_a": false,
  "cb_360_g": false,
  "cb_361_r": false,
  "cb_361_a": false,
  "cb_361_g": false,
  "cb_362_r": false,
  "cb_362_a": false,
  "cb_362_g": false,
  "cb_363_r": false,
  "cb_363_a": false,
  "cb_363_g": true,
  "cb_364_r": false,
  "cb_364_a": false,
  "cb_364_g": true,
  "cb_365_r": false,
  "cb_365_a": false,
  "cb_365_g": true,
  "cb_366_r": false,
  "cb_366_a": false,
  "cb_366_g": true,
  "cb_367_r": false,
  "cb_367_a": true,
  "cb_367_g": false,
  "cb_368_r": false,
  "cb_368_a": true,
  "cb_368_g": false,
  "cb_369_r": false,
  "cb_369_a": false,
  "cb_369_g": true,
  "cb_370_r": false,
  "cb_370_a": false,
  "cb_370_g": true,
  "cb_371_r": false,
  "cb_371_a": false,
  "cb_371_g": true,
  "cb_372_r": false,
  "cb_372_a": false,
  "cb_372_g": true,
  "cb_373_r": false,
  "cb_373_a": false,
  "cb_373_g": true,
  "cb_374_r": false,
  "cb_374_a": false,
  "cb_374_g": true,
  "cb_375_r": false,
  "cb_375_a": false,
  "cb_375_g": true,
  "cb_376_r": false,
  "cb_376_a": true,
  "cb_376_g": false,
  "cb_377_r": false,
  "cb_377_a": false,
  "cb_377_g": true,
  "cb_378_r": false,
  "cb_378_a": false,
  "cb_378_g": true,
  "cb_379_r": false,
  "cb_379_a": false,
  "cb_379_g": true,
  "cb_380_r": false,
  "cb_380_a": false,
  "cb_380_g": false,
  "cb_381_r": false,
  "cb_381_a": false,
  "cb_381_g": false
}